invenio_campusonline/__init__.py
invenio_campusonline/api.py
invenio_campusonline/cli.py
invenio_campusonline/config.py
invenio_campusonline/ext.py
invenio_campusonline/jobs.py
invenio_campusonline/proxies.py
invenio_campusonline/tasks.py
invenio_campusonline/types.py
invenio_campusonline/utils.py
invenio_campusonline/records/__init__.py
invenio_campusonline/records/api.py
invenio_campusonline/records/config.py
invenio_campusonline/records/models.py
invenio_campusonline/services/__init__.py
invenio_campusonline/services/config.py
invenio_campusonline/services/decorators.py
invenio_campusonline/services/services.py
invenio_campusonline-0.6.1.dist-info/licenses/AUTHORS.rst
invenio_campusonline-0.6.1.dist-info/licenses/LICENSE
invenio_campusonline-0.6.1.dist-info/METADATA
invenio_campusonline-0.6.1.dist-info/WHEEL
invenio_campusonline-0.6.1.dist-info/entry_points.txt
invenio_campusonline-0.6.1.dist-info/top_level.txt
invenio_campusonline-0.6.1.dist-info/RECORD
