Metadata-Version: 2.4
Name: invenio-campusonline
Version: 0.6.1
Summary: "The module is used to import/export from/to the CampusOnline System."
Home-page: https://github.com/tu-graz-library/invenio-campusonline
Author: Graz University of Technology
Author-email: info@tugraz.at
License: MIT
Keywords: invenio TODO
Platform: any
Classifier: Programming Language :: Python :: 3.12
Classifier: Programming Language :: Python :: 3.13
Classifier: Development Status :: 5 - Production/Stable
Requires-Python: >=3.12
License-File: LICENSE
License-File: AUTHORS.rst
Requires-Dist: click>=8.0.0
Requires-Dist: click-params>=0.4.0
Requires-Dist: invenio-access>=2.0.0
Requires-Dist: invenio-accounts>=3.0.0
Requires-Dist: invenio-celery>=1.2.5
Requires-Dist: invenio-jobs>=3.0.0
Requires-Dist: requests>=2.0.0
Provides-Extra: tests
Requires-Dist: invenio-app>=2.0.0; extra == "tests"
Requires-Dist: pytest-black-ng>=0.4.0; extra == "tests"
Requires-Dist: pytest-invenio>=1.4.0; extra == "tests"
Requires-Dist: ruff>=0.2.1; extra == "tests"
Requires-Dist: sphinx>=4.5; extra == "tests"
Dynamic: license-file
